commands/__init__.py
commands/help_command.py
commands/name_command.py
commands/settings.py
line_bot_tool/__init__.py
line_bot_tool/utils.py
line_bot_tool/base/__init__.py
line_bot_tool/base/commnad.py
line_bot_tool/base/generator.py
line_bot_tool/core/__init__.py
line_bot_tool/core/generator/__init__.py
line_bot_tool/core/generator/command_generator.py
line_bot_tool-1.0.dist-info/LICENSE
line_bot_tool-1.0.dist-info/METADATA
line_bot_tool-1.0.dist-info/WHEEL
line_bot_tool-1.0.dist-info/entry_points.txt
line_bot_tool-1.0.dist-info/top_level.txt
line_bot_tool-1.0.dist-info/RECORD
