Metadata-Version: 2.1
Name: line-bot-tool
Version: 1.0
Summary: Useful tool for line bot
Home-page: https://github.com/nanato12/line-bot-tool
Author: nanato12
Author-email: admin@nanato12.info
License: Apache License 2.0
Keywords: line-bot line useful tool
Platform: UNKNOWN
Classifier: License :: OSI Approved :: Apache Software License
Classifier: Programming Language :: Python :: 3
Classifier: Programming Language :: Python :: 3 :: Only
Classifier: Programming Language :: Python :: 3.6
Classifier: Programming Language :: Python :: 3.7
Classifier: Programming Language :: Python :: 3.8
Classifier: Programming Language :: Python :: 3.9
Requires-Python: >=3.6
License-File: LICENSE
Requires-Dist: astor
